README.rst
setup.py
pep8ify/__init__.py
pep8ify/pep8ify.py
pep8ify.egg-info/PKG-INFO
pep8ify.egg-info/SOURCES.txt
pep8ify.egg-info/dependency_links.txt
pep8ify.egg-info/entry_points.txt
pep8ify.egg-info/top_level.txt
pep8ify/fixes/__init__.py
pep8ify/fixes/fix_blank_lines.py
pep8ify/fixes/fix_compound_statements.py
pep8ify/fixes/fix_extraneous_whitespace.py
pep8ify/fixes/fix_imports_on_separate_lines.py
pep8ify/fixes/fix_indentation.py
pep8ify/fixes/fix_maximum_line_length.py
pep8ify/fixes/fix_missing_newline.py
pep8ify/fixes/fix_missing_whitespace.py
pep8ify/fixes/fix_tabs.py
pep8ify/fixes/fix_trailing_blank_lines.py
pep8ify/fixes/fix_trailing_whitespace.py
pep8ify/fixes/fix_whitespace_around_operator.py
pep8ify/fixes/fix_whitespace_before_inline_comment.py
pep8ify/fixes/fix_whitespace_before_parameters.py
pep8ify/fixes/utils.py