Metadata-Version: 1.1
Name: pep8ify
Version: 0.0.9
Summary: Cleans your python code to conform to pep8
Home-page: https://github.com/spulec/pep8ify
Author: Steve Pulec
Author-email: spulec@gmail.com
License: Apache License 2.0
Platform: UNKNOWN
Classifier: Environment :: Console
Classifier: Intended Audience :: Developers
Classifier: Programming Language :: Python
Classifier: Topic :: Software Development
Classifier: Topic :: Utilities
